feistel/__init__.py
feistel/__main__.py
feistel/cipher.py
feistel/custom.py
feistel/fpe.py
feistel/utils/__init__.py
feistel/utils/base256.py
feistel/utils/bytearray.py
feistel/utils/hash.py
feistel/utils/padding.py
feistel/utils/strings.py
feistel/utils/xor.py
feistel_py-1.0.1.dist-info/licenses/LICENSE
feistel_py-1.0.1.dist-info/METADATA
feistel_py-1.0.1.dist-info/WHEEL
feistel_py-1.0.1.dist-info/entry_points.txt
feistel_py-1.0.1.dist-info/top_level.txt
feistel_py-1.0.1.dist-info/RECORD
