Metadata-Version: 2.4
Name: feistel-py
Version: 1.0.1
Summary: Feistel cipher implementation in Python for format-preserving encryption
Author-email: Cyril Dever <cdever@pep-s.com>
License: MIT License
Project-URL: Homepage, https://github.com/cyrildever/feistel-py
Keywords: feistel,cipher,format-preserving,encryption,fpe
Classifier: Programming Language :: Python :: 3
Classifier: License :: OSI Approved :: MIT License
Classifier: Operating System :: OS Independent
Requires-Python: >=3.10.2
License-File: LICENSE
Requires-Dist: pycryptodome>=3.23.0
Requires-Dist: py-utls>=0.3.1
Dynamic: license-file
